ecsapi/__init__.py
ecsapi/_action.py
ecsapi/_api.py
ecsapi/_cloud_script.py
ecsapi/_discount_record.py
ecsapi/_image.py
ecsapi/_plan.py
ecsapi/_region.py
ecsapi/_server.py
ecsapi/_server_support.py
ecsapi/_snapshot.py
ecsapi/_ssh_key.py
ecsapi/errors.py
ecsapi/utils.py
ecsapi-0.3.0.dist-info/LICENSE
ecsapi-0.3.0.dist-info/METADATA
ecsapi-0.3.0.dist-info/WHEEL
ecsapi-0.3.0.dist-info/RECORD
