Metadata-Version: 2.3
Name: ecsapi
Version: 0.3.0
Summary: A simple SDK for manage Seeweb ecs api
License: This is free and unencumbered software released into the public domain.
Author: Alex Massaroni
Author-email: alex.m@seeweb.it
Maintainer: Alex Massaroni
Maintainer-email: alex.m@seeweb.it
Requires-Python: >=3.9,<4.0
Classifier: Environment :: Web Environment
Classifier: Intended Audience :: Developers
Classifier: License :: OSI Approved :: The Unlicense (Unlicense)
Classifier: Operating System :: OS Independent
Classifier: Programming Language :: Python :: 3 :: Only
Classifier: Programming Language :: Python :: 3.8
Classifier: Programming Language :: Python :: 3.9
Classifier: Programming Language :: Python :: 3.10
Classifier: Programming Language :: Python :: 3.11
Classifier: Programming Language :: Python :: 3.12
Classifier: Topic :: Software Development :: Libraries :: Python Modules
Requires-Dist: pydantic (>=2.11.7,<3.0.0)
Requires-Dist: python-dotenv (>=1.1.1,<2.0.0)
Requires-Dist: requests (>=2.32.5,<3.0.0)
Project-URL: Homepage, https://github.com/rh363/ecsapi_client
Project-URL: Issues, https://github.com/rh363/ecsapi_client/issues
